FeatTS/PFA.py
FeatTS/SLPA.py
FeatTS/__init__.py
FeatTS/featTS_core.py
FeatTS/utilFeatExtr.py
FeatTS-0.0.3.dist-info/LICENSE
FeatTS-0.0.3.dist-info/METADATA
FeatTS-0.0.3.dist-info/WHEEL
FeatTS-0.0.3.dist-info/top_level.txt
FeatTS-0.0.3.dist-info/zip-safe
FeatTS-0.0.3.dist-info/RECORD
